d4rk/__init__.py
d4rk/_base.py
d4rk/_bot_manager.py
d4rk/Database/__init__.py
d4rk/Database/db.py
d4rk/Handlers/__init__.py
d4rk/Handlers/_bot.py
d4rk/Handlers/_custom.py
d4rk/Handlers/_logger_bot.py
d4rk/Logs/__init__.py
d4rk/Logs/_logger.py
d4rk/Utils/__init__.py
d4rk/Utils/_buttons.py
d4rk/Utils/_decorators.py
d4rk/Utils/_filters.py
d4rk/Utils/_fonts.py
d4rk/Utils/_ip.py
d4rk/Utils/_movie_parser.py
d4rk/Utils/_ractions.py
d4rk/Utils/_terminal.py
d4rk/Utils/_utils.py
d4rk/Web/__init__.py
d4rk/Web/web.py
d4rk/Web/web_server.py
d4rk/errors/__init__.py
d4rk/errors/base.py
d4rk/errors/bot.py
d4rk/errors/config.py
d4rk/errors/database.py
d4rktg-1.5.8.dist-info/METADATA
d4rktg-1.5.8.dist-info/WHEEL
d4rktg-1.5.8.dist-info/top_level.txt
d4rktg-1.5.8.dist-info/RECORD
