Metadata-Version: 2.4
Name: d4rktg
Version: 1.5.8
Summary: A module for create with easy and fast
Author: D4rkShell
Author-email: premiumqtrst@gmail.com
Keywords: python,telegram bot,D4rkShell
Classifier: Development Status :: 1 - Planning
Classifier: Intended Audience :: Developers
Classifier: Programming Language :: Python :: 3
Classifier: Operating System :: OS Independent
Requires-Dist: pyrofork==2.3.68
Requires-Dist: pymongo==4.14.1
Requires-Dist: python-dotenv==1.1.1
Requires-Dist: parse-torrent-title==2.8.1
Requires-Dist: colorama==0.4.6
Requires-Dist: cachetools==6.2.0
Requires-Dist: python-telegram-bot==22.3
Requires-Dist: aiohttp-jinja2==1.6
Requires-Dist: schedule==1.2.2
Requires-Dist: requests==2.32.4
Requires-Dist: aiohttp==3.13.0
Dynamic: author
Dynamic: author-email
Dynamic: classifier
Dynamic: description
Dynamic: description-content-type
Dynamic: keywords
Dynamic: requires-dist
Dynamic: summary
